vidal/client.py
vidal/__init__.py
vidal_api.py-0.0.0.dist-info/metadata.json
vidal_api.py-0.0.0.dist-info/METADATA
vidal_api.py-0.0.0.dist-info/RECORD
vidal_api.py-0.0.0.dist-info/top_level.txt
vidal_api.py-0.0.0.dist-info/DESCRIPTION.rst
vidal_api.py-0.0.0.dist-info/WHEEL
