Metadata-Version: 2.0
Name: vidal-api.py
Version: 0.0.0
Summary: VIDAL REST API - SDK for api.vidal.fr
Home-page: https://github.com/softwarevidal/vidal-api.py
Author: Software VIDAL
Author-email: software@vidal.fr
License: UNKNOWN
Platform: UNKNOWN
Classifier: Development Status :: 3 - Alpha
Classifier: Intended Audience :: Developers
Classifier: License :: OSI Approved :: Apache Software License
Classifier: Natural Language :: English
Classifier: Operating System :: OS Independent
Classifier: Programming Language :: Python
Classifier: Topic :: Software Development :: Libraries :: Python Modules
Classifier: Topic :: Utilities
Requires-Dist: requests
Requires-Dist: feedparser
